appsalutely/__init__.py
appsalutely/email/imap.py
appsalutely/email/settings.py
appsalutely/email/smtp.py
appsalutely/email/utils.py
appsalutely/filters.py
appsalutely/py.typed
appsalutely-0.1.9.dist-info/WHEEL
appsalutely-0.1.9.dist-info/METADATA
appsalutely-0.1.9.dist-info/RECORD
