Metadata-Version: 2.3
Name: appsalutely
Version: 0.1.9
Summary: A utility library for building apps with FastAPI and Vue.js
Keywords: fastapi,vue,utility,library
License: MIT
Classifier: Programming Language :: Python :: 3.12
Classifier: Framework :: FastAPI
Classifier: License :: OSI Approved :: MIT License
Classifier: Operating System :: OS Independent
Requires-Dist: fastapi>=0.115.12 ; extra == 'fastapi'
Requires-Dist: tortoise-orm>=0.25.0 ; extra == 'tortoise'
Requires-Python: >=3.12
Project-URL: homepage, https://github.com/merlinz01/appsalutely
Project-URL: repository, https://github.com/merlinz01/appsalutely
Provides-Extra: fastapi
Provides-Extra: tortoise
